setup.py
Products/__init__.py
Products.qRSS2Syndication.egg-info/PKG-INFO
Products.qRSS2Syndication.egg-info/SOURCES.txt
Products.qRSS2Syndication.egg-info/dependency_links.txt
Products.qRSS2Syndication.egg-info/namespace_packages.txt
Products.qRSS2Syndication.egg-info/not-zip-safe
Products.qRSS2Syndication.egg-info/requires.txt
Products.qRSS2Syndication.egg-info/top_level.txt
Products/qRSS2Syndication/HISTORY.txt
Products/qRSS2Syndication/README.txt
Products/qRSS2Syndication/TODO.txt
Products/qRSS2Syndication/__init__.py
Products/qRSS2Syndication/config.py
Products/qRSS2Syndication/refresh.txt
Products/qRSS2Syndication/utils.py
Products/qRSS2Syndication/version.txt
Products/qRSS2Syndication/Extensions/Install.py
Products/qRSS2Syndication/Extensions/__init__.py
Products/qRSS2Syndication/skins/qrss2syndication/RSS1.dtml
Products/qRSS2Syndication/skins/qrss2syndication/RSS2.pt
Products/qRSS2Syndication/skins/qrss2syndication/ataudio_item.pt
Products/qRSS2Syndication/skins/qrss2syndication/atvideo_item.pt
Products/qRSS2Syndication/skins/qrss2syndication/bittorrentfile_item.pt
Products/qRSS2Syndication/skins/qrss2syndication/blogentry_item.pt
Products/qRSS2Syndication/skins/qrss2syndication/default_item.pt
Products/qRSS2Syndication/skins/qrss2syndication/document_item.pt
Products/qRSS2Syndication/skins/qrss2syndication/file_item.pt
Products/qRSS2Syndication/skins/qrss2syndication/getFileFieldContentType.py
Products/qRSS2Syndication/skins/qrss2syndication/getItemMacros.py
Products/qRSS2Syndication/skins/qrss2syndication/getObjectCreator.py
Products/qRSS2Syndication/skins/qrss2syndication/getSynProp.py
Products/qRSS2Syndication/skins/qrss2syndication/getSyndicatableContent.py
Products/qRSS2Syndication/skins/qrss2syndication/image_item.pt
Products/qRSS2Syndication/skins/qrss2syndication/mediacoopaudio_item.pt
Products/qRSS2Syndication/skins/qrss2syndication/mediacoopimage_item.pt
Products/qRSS2Syndication/skins/qrss2syndication/mediacoopvideo_item.pt
Products/qRSS2Syndication/skins/qrss2syndication/rss2_icon.png
Products/qRSS2Syndication/skins/qrss2syndication/rssBody1.pt
Products/qRSS2Syndication/skins/qrss2syndication/save_rss2_setup.cpy
Products/qRSS2Syndication/skins/qrss2syndication/save_rss2_setup.cpy.metadata
Products/qRSS2Syndication/skins/qrss2syndication/setup_rss2.cpt
