Metadata-Version: 1.0
Name: Products.qRSS2Syndication
Version: 0.5.1
Summary: Extended syndication support for Plone 3
Home-page: http://pypi.python.org/pypi/Products.qRSS2Syndication
Author: Andreas Jung
Author-email: info@zopyx.com
License: UNKNOWN
Platform: UNKNOWN
Classifier: Programming Language :: Python
Classifier: Framework :: Zope2
Classifier: Framework :: Plone
